codegen_git/py.typed
codegen_git/clients/git_integration_client.py
codegen_git/clients/git_repo_client.py
codegen_git/clients/github_client.py
codegen_git/clients/github_client_factory.py
codegen_git/clients/github_enterprise_client.py
codegen_git/clients/types.py
codegen_git/configs/config.py
codegen_git/configs/constants.py
codegen_git/configs/token.py
codegen_git/repo_operator/local_repo_operator.py
codegen_git/repo_operator/remote_repo_operator.py
codegen_git/repo_operator/repo_operator.py
codegen_git/schemas/enums.py
codegen_git/schemas/github.py
codegen_git/schemas/repo_config.py
codegen_git/utils/clone.py
codegen_git/utils/clone_url.py
codegen_git/utils/codeowner_utils.py
codegen_git/utils/file_utils.py
codegen_git/utils/format.py
codegen_git/utils/remote_progress.py
codegen_git/utils/stopwatch_utils.py
codegen_git/utils/time_utils.py
codegen_git-7.0.1.dist-info/METADATA
codegen_git-7.0.1.dist-info/WHEEL
codegen_git-7.0.1.dist-info/RECORD
