Metadata-Version: 2.4
Name: codegen-git
Version: 7.0.1
License: 
Classifier: License :: OSI Approved :: Apache Software License
Requires-Python: >=3.9
Requires-Dist: codeowners>=0.7.0
Requires-Dist: gitpython==3.1.44
Requires-Dist: pygithub==2.5.0
Requires-Dist: termcolor>=2.4.0
